opentronsfastapi/__init__.py
opentronsfastapi-0.1.0.dist-info/LICENSE
opentronsfastapi-0.1.0.dist-info/METADATA
opentronsfastapi-0.1.0.dist-info/WHEEL
opentronsfastapi-0.1.0.dist-info/top_level.txt
opentronsfastapi-0.1.0.dist-info/RECORD
