Metadata-Version: 2.1
Name: opentronsfastapi
Version: 0.1.0
Summary: opentronsfastapi is package for building FastAPIs that run protocols on an Opentrons
Home-page: https://github.com/Koeng101/opentronsfastapi
Author: Keoni Gandall, Tim Dobbs
Author-email: keoni@sporenetlabs.com, timdobbs@gmail.com
License: UNKNOWN
Platform: UNKNOWN
License-File: LICENSE
